adaMVP_new/adj_mat_interactome.py
adaMVP_new/graph_builder.py
adaMVP_new/graphical_models.py
adaMVP_new/markov_model_dataframe.py
adaMVP_new/mvp_build_graph.py
adaMVP_new/sig_first_neighbors.py
adaMVP_new/study_bias.py
adaMVP_new/data/publications_all_genes.txt
adaMVP_new/data/unique_interactome_CanSAR_KEGG_reaction_updated_Hi_union_043024.txt
adamvp_new-2.0.3.dist-info/licenses/LICENSE.txt
adamvp_new-2.0.3.dist-info/METADATA
adamvp_new-2.0.3.dist-info/WHEEL
adamvp_new-2.0.3.dist-info/top_level.txt
adamvp_new-2.0.3.dist-info/RECORD
