Metadata-Version: 2.4
Name: adaMVP_new
Version: 2.0.3
Summary: Adaptive AI-Augmented Drug Discovery and Development Molecular Vulnerability Picker
Author-email: Ying Zhu <yzhu16@mdanderson.org>
Project-URL: Homepage, https://github.com/YingZ-A3D3a/A3D3a_MVP_new
Classifier: Programming Language :: Python :: 3
Classifier: License :: OSI Approved :: MIT License
Classifier: Operating System :: OS Independent
Requires-Python: >=3.8
License-File: LICENSE.txt
Requires-Dist: numpy>1.21
Requires-Dist: pandas>1.4
Requires-Dist: matplotlib>3.5
Requires-Dist: networkx>2.7
Requires-Dist: tqdm
Requires-Dist: statsmodels>0.13
Requires-Dist: seaborn>0.11
Dynamic: license-file
